ghastly/__about__.py
ghastly/__init__.py
ghastly/core.py
ghastly/material.py
ghastly/pebble.py
ghastly/region.py
ghastly/simulation.py
ghastly-0.2.0.dist-info/METADATA
ghastly-0.2.0.dist-info/WHEEL
ghastly-0.2.0.dist-info/licenses/LICENSE
ghastly-0.2.0.dist-info/RECORD
