Metadata-Version: 2.3
Name: ghastly
Version: 0.2.0
Summary: Pebble packing and movement tool
Author-email: Zoe Richter <zoerichter96@gmail.com>
License: BSD 3-Clause License
License-File: LICENSE
Requires-Python: >=3.8
